{
  "project_info": {
    "project_number": "247039423050",
    "project_id": "fit5046l3g4findaslot",
    "storage_bucket": "fit5046l3g4findaslot.appspot.com"
  },
  "client": [
    {
      "client_info": {
        "mobilesdk_app_id": "1:247039423050:android:94dbcd129bccb49c1bacb3",
        "android_client_info": {
          "package_name": "com.example.findaslot"
        }
      },
      "oauth_client": [],
      "api_key": [
        {
          "current_key": ""
        }
      ],
      "services": {
        "appinvite_service": {
          "other_platform_oauth_client": []
        }
      }
    }
  ],
  "configuration_version": "1"
}
